CHANGES.md
MANIFEST.in
README.md
setup.py
support_validators.md
Django_Bootstrap3_Validator.egg-info/PKG-INFO
Django_Bootstrap3_Validator.egg-info/SOURCES.txt
Django_Bootstrap3_Validator.egg-info/dependency_links.txt
Django_Bootstrap3_Validator.egg-info/top_level.txt
bootstrap_validator/__init__.py
bootstrap_validator/tests.py
bootstrap_validator/validators.py
bootstrap_validator/migrations/__init__.py
bootstrap_validator/static/validator/css/bootstrapValidator.css
bootstrap_validator/static/validator/css/bootstrapValidator.min.css
bootstrap_validator/static/validator/js/bootstrapValidator.js
bootstrap_validator/static/validator/js/bootstrapValidator.min.js
bootstrap_validator/static/validator/js/language/ar_MA.js
bootstrap_validator/static/validator/js/language/be_FR.js
bootstrap_validator/static/validator/js/language/be_NL.js
bootstrap_validator/static/validator/js/language/bg_BG.js
bootstrap_validator/static/validator/js/language/cs_CZ.js
bootstrap_validator/static/validator/js/language/da_DK.js
bootstrap_validator/static/validator/js/language/de_DE.js
bootstrap_validator/static/validator/js/language/en_US.js
bootstrap_validator/static/validator/js/language/es_CL.js
bootstrap_validator/static/validator/js/language/es_ES.js
bootstrap_validator/static/validator/js/language/fa_IR.js
bootstrap_validator/static/validator/js/language/fr_FR.js
bootstrap_validator/static/validator/js/language/gr_EL.js
bootstrap_validator/static/validator/js/language/he_IL.js
bootstrap_validator/static/validator/js/language/hu_HU.js
bootstrap_validator/static/validator/js/language/id_ID.js
bootstrap_validator/static/validator/js/language/it_IT.js
bootstrap_validator/static/validator/js/language/ja_JP.js
bootstrap_validator/static/validator/js/language/nl_NL.js
bootstrap_validator/static/validator/js/language/no_NO.js
bootstrap_validator/static/validator/js/language/pl_PL.js
bootstrap_validator/static/validator/js/language/pt_BR.js
bootstrap_validator/static/validator/js/language/pt_PT.js
bootstrap_validator/static/validator/js/language/ro_RO.js
bootstrap_validator/static/validator/js/language/ru_RU.js
bootstrap_validator/static/validator/js/language/sq_AL.js
